p3dae/__init__.py
p3dae/audio_effects.py
p3dae-0.1.0.dist-info/LICENSE
p3dae-0.1.0.dist-info/METADATA
p3dae-0.1.0.dist-info/WHEEL
p3dae-0.1.0.dist-info/top_level.txt
p3dae-0.1.0.dist-info/RECORD
