Metadata-Version: 2.1
Name: p3dae
Version: 0.1.0
Summary: p3dae - audio effects library for Panda3D
Home-page: https://github.com/moonburnt/p3dae
Author: moonburnt
Author-email: moonburnt@disroot.org
License: MIT
Platform: UNKNOWN
Classifier: Programming Language :: Python :: 3
Requires-Dist: panda3d (>=1.10)
